woofipro/__init__.py
woofipro/ccxt/__init__.py
woofipro/ccxt/woofipro.py
woofipro/ccxt/abstract/woofipro.py
woofipro/ccxt/async_support/__init__.py
woofipro/ccxt/async_support/woofipro.py
woofipro/ccxt/async_support/base/__init__.py
woofipro/ccxt/async_support/base/exchange.py
woofipro/ccxt/async_support/base/throttler.py
woofipro/ccxt/async_support/base/ws/__init__.py
woofipro/ccxt/async_support/base/ws/cache.py
woofipro/ccxt/async_support/base/ws/client.py
woofipro/ccxt/async_support/base/ws/functions.py
woofipro/ccxt/async_support/base/ws/future.py
woofipro/ccxt/async_support/base/ws/order_book.py
woofipro/ccxt/async_support/base/ws/order_book_side.py
woofipro/ccxt/base/__init__.py
woofipro/ccxt/base/decimal_to_precision.py
woofipro/ccxt/base/errors.py
woofipro/ccxt/base/exchange.py
woofipro/ccxt/base/precise.py
woofipro/ccxt/base/types.py
woofipro/ccxt/pro/__init__.py
woofipro/ccxt/pro/woofipro.py
woofipro/ccxt/static_dependencies/README.md
woofipro/ccxt/static_dependencies/__init__.py
woofipro/ccxt/static_dependencies/bip/__init__.py
woofipro/ccxt/static_dependencies/bip/addr/P2PKH_addr.py
woofipro/ccxt/static_dependencies/bip/addr/__init__.py
woofipro/ccxt/static_dependencies/bip/addr/addr_dec_utils.py
woofipro/ccxt/static_dependencies/bip/addr/addr_key_validator.py
woofipro/ccxt/static_dependencies/bip/addr/iaddr_decoder.py
woofipro/ccxt/static_dependencies/bip/addr/iaddr_encoder.py
woofipro/ccxt/static_dependencies/bip/base58/__init__.py
woofipro/ccxt/static_dependencies/bip/base58/base58.py
woofipro/ccxt/static_dependencies/bip/base58/base58_ex.py
woofipro/ccxt/static_dependencies/bip/base58/base58_xmr.py
woofipro/ccxt/static_dependencies/bip/bech32/__init__.py
woofipro/ccxt/static_dependencies/bip/bech32/bch_bech32.py
woofipro/ccxt/static_dependencies/bip/bech32/bech32.py
woofipro/ccxt/static_dependencies/bip/bech32/bech32_base.py
woofipro/ccxt/static_dependencies/bip/bech32/bech32_ex.py
woofipro/ccxt/static_dependencies/bip/bech32/segwit_bech32.py
woofipro_api-0.0.119.dist-info/METADATA
woofipro_api-0.0.119.dist-info/WHEEL
woofipro_api-0.0.119.dist-info/RECORD
